[
  {
    "id": "12345ABCDE",
    "vehicle": {
      "make": "Toyota",
      "model": "4Runner",
      "year": 1990
    },
    "service": []
  },
  {
    "id": "69870ABCDE",
    "vehicle": {
      "make": "Chevrolet",
      "model": "Suburban",
      "year": 2010
    },
    "service": [
      {
        "date": 1471212546816,
        "location": "Castrol Xpress Lube",
        "mileage": 114834,
        "work": [
          "Auto Transmission Flush",
          "Power Steering Flush",
          "Transfer Case Service"
        ]
      }
    ]
  }
]
